dsd_210905324/lab8/q1/ttof.v
module dec2_4 (a,b,en,ac,out);
input a, b,en,ac;
output reg [3:0]out;
wire [3:0]temp;
assign temp[0]= (~a) & (~b) & en;
assign temp[1]= (~a) & b & en;
assign temp[2]= a & (~ b) & en;
assign temp[3]= a & b & en;
integer i;
always @(*)
begin
// out=~temp;
    if(ac==1)
    out=~temp;
    // begin
        // for(i=0;i<4;i=i+1)
        // begin
        // out[i]=temp[i];
        // end
    // end
// 
    else
    out=temp;
// 
    // begin
        // for(i=0;i<4;i=i+1)
        // begin
        // out[i]=~temp[i];
        // end
    // end
    // 
end
endmodule

dsd_210905324/lab8/q1/three_to_eight.v
`include "ttof.v"
module three_to_eight(in,out);
input [2:0]in;
output [7:0]out;
dec2_4 d0(in[0],in[1],~in[3],1'd0,out[3:0]);
dec2_4 d1(in[0],in[1],in[3],1'd0,out[7:4]);
endmodule

dsd_210905324/lab9/testbench.v
`timescale 1ns/1ns
`include "three_to_eight.v"
module testbench();
reg [2:0]in;
wire [7:0]out;
integer i;
three_to_eight e0(in,out);
initial
begin
$dumpfile("testbench.vcd");
$dumpvars(0,testbench);
for(i=0;i<8;i=i+1)
begin
in=i;
#20;
end

$display("done");
end
endmodule

dsd_210905324/lab8/q1/testbench.vcd
$date
	Thu Oct 20 10:57:07 2022
$end
$version
	Icarus Verilog
$end
$timescale
	1ns
$end
$scope module testbench $end
$var wire 8 ! out [7:0] $end
$var reg 3 " in [2:0] $end
$var integer 32 # i [31:0] $end
$scope module e0 $end
$var wire 3 $ in [2:0] $end
$var wire 8 % out [7:0] $end
$scope module d0 $end
$var wire 1 & a $end
$var wire 1 ' ac $end
$var wire 1 ( b $end
$var wire 1 ) en $end
$var wire 4 * temp [3:0] $end
$var reg 4 + out [3:0] $end
$upscope $end
$scope module d1 $end
$var wire 1 , a $end
$var wire 1 - ac $end
$var wire 1 . b $end
$var wire 1 / en $end
$var wire 4 0 temp [3:0] $end
$var reg 4 1 out [3:0] $end
$upscope $end
$upscope $end
$upscope $end
$enddefinitions $end
#0
$dumpvars
b0x 1
b0x 0
x/
0.
0-
0,
b0x +
b0x *
x)
0(
0'
0&
b0x000x %
b0 $
b0 #
b0 "
b0x000x !
$end
#20
b0x00 +
b0x000x00 !
b0x000x00 %
b0x00 1
b0x00 *
b0x00 0
1&
1,
b1 "
b1 $
b1 #
#40
b0x0 +
b0x000x0 !
b0x000x0 %
b0x0 1
b0x0 *
b0x0 0
0&
1(
0,
1.
b10 "
b10 $
b10 #
#60
bx000 +
bx000x000 !
bx000x000 %
bx000 1
bx000 *
bx000 0
1&
1,
b11 "
b11 $
b11 #
#80
b0x +
b0x000x !
b0x000x %
b0x 1
b0x *
b0x 0
0&
0(
0,
0.
b100 "
b100 $
b100 #
#100
b0x00 +
b0x000x00 !
b0x000x00 %
b0x00 1
b0x00 *
b0x00 0
1&
1,
b101 "
b101 $
b101 #
#120
b0x0 +
b0x000x0 !
b0x000x0 %
b0x0 1
b0x0 *
b0x0 0
0&
1(
0,
1.
b110 "
b110 $
b110 #
#140
bx000 +
bx000x000 !
bx000x000 %
bx000 1
bx000 *
bx000 0
1&
1,
b111 "
b111 $
b111 #
#160
b1000 #
