dsd_210905324/lab7/q1a/q1.v
module caller(sel,out);
    input [3:0] sel;
    output out;
    eto1 s0(sel,out);
endmodule

module eto1(sel,out);
    input [3:0] sel;
    output out;
    reg out;
    always @(sel,out)
    begin
        if(sel[2:1]==0)
            out=~sel[1]|sel[0];
        if(sel[2:1]==1)
            out=sel[0];
        if(sel[2:1]==2)
            out=0;
        if(sel[2:1]==3)
            out=0;
       
        
    end
        
endmodule

dsd_210905324/lab7/q1a/q1_tb.v
`timescale 1ns/1ns
`include "q1.v"
module q1_tb();
reg [3:0] sel;
wire out;

eto1 q1(sel,out);
initial
begin
    $dumpfile("q1_tb.vcd");
    $dumpvars(0,q1_tb);
    sel=4'b0001;#20;
    sel=4'b0010;#20;
    sel=4'b0011;#20;
    sel=4'b0100;#20;
    sel=4'b1100;#20;
    sel=4'b1110;#20;
    sel=4'b1111;#20;
    sel=4'b0111;#20;
    sel=4'b0101;#20;
    sel=4'b1101;#20;

    $display("test complete");
end
endmodule

dsd_210905324/lab7/q1a/q1_tb.vcd
$date
	Thu Oct 13 11:16:23 2022
$end
$version
	Icarus Verilog
$end
$timescale
	1ns
$end
$scope module q1_tb $end
$var wire 1 ! out $end
$var reg 4 " sel [3:0] $end
$scope module q1 $end
$var wire 4 # sel [3:0] $end
$var reg 1 ! out $end
$upscope $end
$upscope $end
$enddefinitions $end
#0
$dumpvars
b1 #
b1 "
0!
$end
#20
b10 "
b10 #
#40
b11 "
b11 #
#60
1!
b100 "
b100 #
#80
b1100 "
b1100 #
#100
0!
b1110 "
b1110 #
#120
b1111 "
b1111 #
#140
1!
b111 "
b111 #
#160
b101 "
b101 #
#180
b1101 "
b1101 #
