dsd_210905324/lab4/1/halfadd.v

module halfadd(x,y,s,c);
input x,y;
output s,c;
assign s = x^y;
assign c = x&y;
endmodule

dsd_210905324/lab4/1/defulladd.v
`include "halfadd.v"
module defulladd(x,y,Cin,s,Cout);
input x,y,Cin;
output s,Cout;
halfadd stage0(x,y,s0,c0);
halfadd stage1(s0,Cin,s,c1);
assign Cout = (c0|c1);
endmodule

dsd_210905324/lab4/1/defulladd_tb.v
`timescale 1ns/1ns
`include "defulladd.v"
//Name of the Verilog file
module defulladd_tb();
reg x,y,Cin;
//Input
wire s,Cout;
//Output
defulladd ex2(x,y,Cin,s,Cout); //Instantiation of the module
initial
begin
$dumpfile("defulladd.vcd");
$dumpvars(0, defulladd_tb);
x=0;y=0;Cin=0;#20
x=0;y=0;Cin=1;#20
x=0;y=1;Cin=0;#20
x=0;y=1;Cin=1;#20
x=1;y=0;Cin=0;#20
x=1;y=0;Cin=1;#20
x=1;y=1;Cin=0;#20
x=1;y=1;Cin=1;#20


$display("Test complete");
end
endmodule

dsd_210905324/lab4/1/defulladd.vcd
$date
	Thu Sep 15 09:47:22 2022
$end
$version
	Icarus Verilog
$end
$timescale
	1ns
$end
$scope module defulladd_tb $end
$var wire 1 ! s $end
$var wire 1 " Cout $end
$var reg 1 # Cin $end
$var reg 1 $ x $end
$var reg 1 % y $end
$scope module ex2 $end
$var wire 1 # Cin $end
$var wire 1 " Cout $end
$var wire 1 $ x $end
$var wire 1 % y $end
$var wire 1 & s0 $end
$var wire 1 ! s $end
$var wire 1 ' c1 $end
$var wire 1 ( c0 $end
$scope module stage0 $end
$var wire 1 ( c $end
$var wire 1 & s $end
$var wire 1 $ x $end
$var wire 1 % y $end
$upscope $end
$scope module stage1 $end
$var wire 1 ' c $end
$var wire 1 ! s $end
$var wire 1 & x $end
$var wire 1 # y $end
$upscope $end
$upscope $end
$upscope $end
$enddefinitions $end
#0
$dumpvars
0(
0'
0&
0%
0$
0#
0"
0!
$end
#20
1!
1#
#40
1&
0#
1%
#60
1"
0!
1'
1#
#80
0"
1!
0'
0#
0%
1$
#100
1"
0!
1'
1#
#120
0'
0&
1(
0#
1%
#140
1!
1#
