dsd_210905324/lab4/1/fulladd.v

module fulladd(Cin,x,y,s,Cout);
input Cin,x,y;
output s,Cout;
assign s = x^y^Cin;
assign Cout = (x&y)|(x&Cin)|(y&Cin);
endmodule

dsd_210905324/lab4/1/fulladd_tb.v
`timescale 1ns/1ns
`include "fulladd.v"
//Name of the Verilog file
module fulladd_tb();
reg x,y,Cin;
//Input
wire s,Cout;
//Output
fulladd ex2(x,y,Cin,s,Cout); //Instantiation of the module
initial
begin
$dumpfile("fulladd.vcd");
$dumpvars(0, fulladd_tb);
x=0;y=0;Cin=0;#20
x=0;y=0;Cin=1;#20
x=0;y=1;Cin=0;#20
x=0;y=1;Cin=1;#20
x=1;y=0;Cin=0;#20
x=1;y=0;Cin=1;#20
x=1;y=1;Cin=0;#20
x=1;y=1;Cin=1;#20


$display("Test complete");
end
endmodule

dsd_210905324/lab4/1/fulladd.vcd
$date
	Thu Sep 15 09:37:40 2022
$end
$version
	Icarus Verilog
$end
$timescale
	1ns
$end
$scope module fulladd_tb $end
$var wire 1 ! s $end
$var wire 1 " Cout $end
$var reg 1 # Cin $end
$var reg 1 $ x $end
$var reg 1 % y $end
$scope module ex2 $end
$var wire 1 $ Cin $end
$var wire 1 " Cout $end
$var wire 1 ! s $end
$var wire 1 % x $end
$var wire 1 # y $end
$upscope $end
$upscope $end
$enddefinitions $end
#0
$dumpvars
0%
0$
0#
0"
0!
$end
#20
1!
1#
#40
0#
1%
#60
1"
0!
1#
#80
0"
1!
0#
0%
1$
#100
0!
1"
1#
#120
0#
1%
#140
1!
1#
