dsd_210905324/lab9/q1/four_to_sixteen.v
module decoder3_to_8( in,out, en);
input [2:0]  in;
input en;
output [7:0] out;
  reg [7:0] out;
integer i;

 always @( in or en)
	begin

      if (en) 
        begin
        out=8'b0;
          for(i=0;i<8;i=i+1)
          begin
            if(in==i)
            begin
            out[i]=1'b1;
            end
          end
      end
else 
out=8'd0;
end
endmodule
module caller(in,out);
input [3:0]in;
output [15:0]out;
decoder3_to_8 d0(in[2:0],out[7:0],~in[3]);
decoder3_to_8 d1(in[2:0],out[15:8],in[3]);
endmodule

dsd_210905324/lab9/q1/caller.v
`include "four_to_sixteen.v"
module exe(in ,out);
input [3:0]in;
output out;
reg out;
wire [15:0]phase;
caller c0(in,phase);
always@(*)
begin
out = phase[1] | phase[3] | phase[6] | phase[7] | phase[9] | phase[14] | phase[15] ;
end
endmodule

dsd_210905324/lab9/q1/testbench.v
`timescale 1ns/1ns
`include "caller.v"
module testbench();
reg [3:0]in;
wire out;
integer i;
exe e0(in,out);
initial
begin
$dumpfile("testbench.vcd");
$dumpvars(0,testbench);
for(i=0;i<16;i=i+1)
begin
in=i;
#20;
end

$display("done");
end
endmodule

dsd_210905324/lab9/q1/testbench.vcd
$date
	Thu Oct 27 09:02:56 2022
$end
$version
	Icarus Verilog
$end
$timescale
	1ns
$end
$scope module testbench $end
$var wire 1 ! out $end
$var reg 4 " in [3:0] $end
$var integer 32 # i [31:0] $end
$scope module e0 $end
$var wire 4 $ in [3:0] $end
$var wire 16 % phase [15:0] $end
$var reg 1 ! out $end
$scope module c0 $end
$var wire 4 & in [3:0] $end
$var wire 16 ' out [15:0] $end
$scope module d0 $end
$var wire 1 ( en $end
$var wire 3 ) in [2:0] $end
$var reg 8 * out [7:0] $end
$var integer 32 + i [31:0] $end
$upscope $end
$scope module d1 $end
$var wire 1 , en $end
$var wire 3 - in [2:0] $end
$var reg 8 . out [7:0] $end
$var integer 32 / i [31:0] $end
$upscope $end
$upscope $end
$upscope $end
$upscope $end
$enddefinitions $end
#0
$dumpvars
bx /
b0 .
b0 -
0,
b1000 +
b1 *
b0 )
1(
b1 '
b0 &
b1 %
b0 $
b0 #
b0 "
0!
$end
#20
1!
b1000 +
b10 %
b10 '
b10 *
b1 )
b1 -
b1 "
b1 $
b1 &
b1 #
#40
0!
b1000 +
b100 %
b100 '
b100 *
b10 )
b10 -
b10 "
b10 $
b10 &
b10 #
#60
1!
b1000 +
b1000 %
b1000 '
b1000 *
b11 )
b11 -
b11 "
b11 $
b11 &
b11 #
#80
0!
b1000 +
b10000 %
b10000 '
b10000 *
b100 )
b100 -
b100 "
b100 $
b100 &
b100 #
#100
b1000 +
b100000 %
b100000 '
b100000 *
b101 )
b101 -
b101 "
b101 $
b101 &
b101 #
#120
1!
b1000 +
b1000000 %
b1000000 '
b1000000 *
b110 )
b110 -
b110 "
b110 $
b110 &
b110 #
#140
b1000 +
b10000000 %
b10000000 '
b10000000 *
b111 )
b111 -
b111 "
b111 $
b111 &
b111 #
#160
0!
b0 *
0(
b100000000 %
b100000000 '
b1 .
b1000 /
b0 )
b0 -
1,
b1000 "
b1000 $
b1000 &
b1000 #
#180
1!
b1000 /
b1000000000 %
b1000000000 '
b10 .
b1 )
b1 -
b1001 "
b1001 $
b1001 &
b1001 #
#200
0!
b1000 /
b10000000000 %
b10000000000 '
b100 .
b10 )
b10 -
b1010 "
b1010 $
b1010 &
b1010 #
#220
b1000 /
b100000000000 %
b100000000000 '
b1000 .
b11 )
b11 -
b1011 "
b1011 $
b1011 &
b1011 #
#240
b1000 /
b1000000000000 %
b1000000000000 '
b10000 .
b100 )
b100 -
b1100 "
b1100 $
b1100 &
b1100 #
#260
b1000 /
b10000000000000 %
b10000000000000 '
b100000 .
b101 )
b101 -
b1101 "
b1101 $
b1101 &
b1101 #
#280
1!
b1000 /
b100000000000000 %
b100000000000000 '
b1000000 .
b110 )
b110 -
b1110 "
b1110 $
b1110 &
b1110 #
#300
b1000 /
b1000000000000000 %
b1000000000000000 '
b10000000 .
b111 )
b111 -
b1111 "
b1111 $
b1111 &
b1111 #
#320
b10000 #
