dsd_210905324/lab9/q3/caller.v
module dec2_to_4(w,y,en);
input [1:0]w;
input en;
output reg [3:0]y;
always@(w or en)
    case({en,w})
    3'b100:y=4'b0111;
    3'b101:y=4'b1011;
    3'b110:y=4'b1101;
    3'b111:y=4'b1110;
    default:y=4'b1111;
    endcase
endmodule

module exe(in,out,en);
input [2:0]in;
input en;
output out;
output [3:0]temp1,temp2,temp3;
dec2_to_4 d0(in[1:0],temp1,(~in[2]&en));
dec2_to_4 d1(in[1:0],temp2,(in[2]&en));
assign out= ~temp1[0] | ~temp2[2] | ~temp2[1] | ~temp2[0];
endmodule

dsd_210905324/lab9/q3/testbench.v
`timescale 1ns/1ns
`include "caller.v"
module testbench();
reg [2:0]in;
wire out;
integer i;
exe e0(in,out,1'b1);
initial
begin
$dumpfile("testbench.vcd");
$dumpvars(0,testbench);
for(i=0;i<8;i=i+1)
begin
in=i;
#20;
end

$display("done");
end
endmodule

dsd_210905324/lab9/q3/testbench.vcd
$date
	Thu Oct 27 10:10:59 2022
$end
$version
	Icarus Verilog
$end
$timescale
	1ns
$end
$scope module testbench $end
$var wire 1 ! out $end
$var reg 3 " in [2:0] $end
$var integer 32 # i [31:0] $end
$scope module e0 $end
$var wire 1 $ en $end
$var wire 3 % in [2:0] $end
$var wire 1 ! out $end
$var wire 4 & temp3 [3:0] $end
$var wire 4 ' temp2 [3:0] $end
$var wire 4 ( temp1 [3:0] $end
$scope module d0 $end
$var wire 1 ) en $end
$var wire 2 * w [1:0] $end
$var reg 4 + y [3:0] $end
$upscope $end
$scope module d1 $end
$var wire 1 , en $end
$var wire 2 - w [1:0] $end
$var reg 4 . y [3:0] $end
$upscope $end
$upscope $end
$upscope $end
$enddefinitions $end
#0
$dumpvars
b1111 .
b0 -
0,
b111 +
b0 *
1)
b111 (
b1111 '
bz &
b0 %
1$
b0 #
b0 "
0!
$end
#20
b1011 (
b1011 +
b1 *
b1 -
b1 "
b1 %
b1 #
#40
b1101 (
b1101 +
b10 *
b10 -
b10 "
b10 %
b10 #
#60
1!
b1110 (
b1110 +
b11 *
b11 -
b11 "
b11 %
b11 #
#80
0!
0)
b1111 (
b1111 +
b111 '
b111 .
1,
b0 *
b0 -
b100 "
b100 %
b100 #
#100
1!
b1011 '
b1011 .
b1 *
b1 -
b101 "
b101 %
b101 #
#120
b1101 '
b1101 .
b10 *
b10 -
b110 "
b110 %
b110 #
#140
b1110 '
b1110 .
b11 *
b11 -
b111 "
b111 %
b111 #
#160
b1000 #
