dsd_210905324/lab8/q2/three_to_eight.v
module decoder3_to_8( in,out, en);
input [2:0]  in;
input en;
output [7:0] out;
  reg [7:0] out;
integer i;

 always @( in or en)
	begin

      if (en) 
        begin
        out=8'b0;
          for(i=0;i<8;i=i+1)
          begin
            if(in==i)
            begin
            out[i]=1'b1;
            end
          end
      end
else 
out=8'd0;
end
endmodule

dsd_210905324/lab8/q2/four_to_sixteen.v
`include "three_to_eight.v"
module caller(in,out);
input [3:0]in;
output [15:0]out;
decoder3_to_8 d0(in[2:0],out[7:0],~in[3]);
decoder3_to_8 d1(in[2:0],out[15:8],in[3]);
endmodule

dsd_210905324/lab8/q2/testbench.v
`timescale 1ns/1ns
`include "four_to_sixteen.v"
module testbench();
reg [3:0]in;
wire [15:0]out;
integer i;
caller e0(in,out);
initial
begin
$dumpfile("testbench.vcd");
$dumpvars(0,testbench);
for(i=0;i<16;i=i+1)
begin
in=i;
#20;
end

$display("done");
end
endmodule

dsd_210905324/lab8/q2/testbench.vcd
$date
	Thu Oct 20 11:19:45 2022
$end
$version
	Icarus Verilog
$end
$timescale
	1ns
$end
$scope module testbench $end
$var wire 16 ! out [15:0] $end
$var reg 4 " in [3:0] $end
$var integer 32 # i [31:0] $end
$scope module e0 $end
$var wire 4 $ in [3:0] $end
$var wire 16 % out [15:0] $end
$scope module d0 $end
$var wire 1 & en $end
$var wire 3 ' in [2:0] $end
$var reg 8 ( out [7:0] $end
$var integer 32 ) i [31:0] $end
$upscope $end
$scope module d1 $end
$var wire 1 * en $end
$var wire 3 + in [2:0] $end
$var reg 8 , out [7:0] $end
$var integer 32 - i [31:0] $end
$upscope $end
$upscope $end
$upscope $end
$enddefinitions $end
#0
$dumpvars
bx -
b0 ,
b0 +
0*
b1000 )
b1 (
b0 '
1&
b1 %
b0 $
b0 #
b0 "
b1 !
$end
#20
b1000 )
b10 !
b10 %
b10 (
b1 '
b1 +
b1 "
b1 $
b1 #
#40
b1000 )
b100 !
b100 %
b100 (
b10 '
b10 +
b10 "
b10 $
b10 #
#60
b1000 )
b1000 !
b1000 %
b1000 (
b11 '
b11 +
b11 "
b11 $
b11 #
#80
b1000 )
b10000 !
b10000 %
b10000 (
b100 '
b100 +
b100 "
b100 $
b100 #
#100
b1000 )
b100000 !
b100000 %
b100000 (
b101 '
b101 +
b101 "
b101 $
b101 #
#120
b1000 )
b1000000 !
b1000000 %
b1000000 (
b110 '
b110 +
b110 "
b110 $
b110 #
#140
b1000 )
b10000000 !
b10000000 %
b10000000 (
b111 '
b111 +
b111 "
b111 $
b111 #
#160
b0 (
0&
b100000000 !
b100000000 %
b1 ,
b1000 -
b0 '
b0 +
1*
b1000 "
b1000 $
b1000 #
#180
b1000 -
b1000000000 !
b1000000000 %
b10 ,
b1 '
b1 +
b1001 "
b1001 $
b1001 #
#200
b1000 -
b10000000000 !
b10000000000 %
b100 ,
b10 '
b10 +
b1010 "
b1010 $
b1010 #
#220
b1000 -
b100000000000 !
b100000000000 %
b1000 ,
b11 '
b11 +
b1011 "
b1011 $
b1011 #
#240
b1000 -
b1000000000000 !
b1000000000000 %
b10000 ,
b100 '
b100 +
b1100 "
b1100 $
b1100 #
#260
b1000 -
b10000000000000 !
b10000000000000 %
b100000 ,
b101 '
b101 +
b1101 "
b1101 $
b1101 #
#280
b1000 -
b100000000000000 !
b100000000000000 %
b1000000 ,
b110 '
b110 +
b1110 "
b1110 $
b1110 #
#300
b1000 -
b1000000000000000 !
b1000000000000000 %
b10000000 ,
b111 '
b111 +
b1111 "
b1111 $
b1111 #
#320
b10000 #
