dsd_210905324/lab3/4/lab2_2.v
module lab2_2(a, b, c,d, f);
input a, b,c,d;
output f;
assign g =~(~(a|c|~d)|~(b|c)|~(b|d));

assign f =~(g|g);

endmodule

dsd_210905324/lab3/4/lab2_2_tb.v
`timescale 1ns/1ns
`include "lab2_2.v"
//Name of the Verilog file
module lab2_2_tb();
reg a,b,c,d;
//Input
wire f;
//Output
lab2_2 ex2(a,b,c,d,f); //Instantiation of the module
initial
begin
$dumpfile("lab2_2.vcd");
$dumpvars(0, lab2_2_tb);
a=1'b0; b=1'b0; c=1'b0;d=1'b0;
#20;

a=1'b0; b=1'b0; c=1'b0;d=1'b1;
#20;
a=1'b0; b=1'b0; c=1'b1;d=1'b0;
#20;
a=1'b0; b=1'b0; c=1'b1;d=1'b1;
#20;
a=1'b0; b=1'b1; c=1'b0;d=1'b0;
#20;
a=1'b0; b=1'b1; c=1'b0;d=1'b1;
#20;
a=1'b0; b=1'b1; c=1'b1;d=1'b0;
#20;
a=1'b0; b=1'b1; c=1'b1;d=1'b1;
#20;
a=1'b1; b=1'b0; c=1'b0;d=1'b0;
#20;
a=1'b1; b=1'b0; c=1'b0;d=1'b1;
#20;
a=1'b1; b=1'b0; c=1'b1;d=1'b0;
#20;
a=1'b1; b=1'b0; c=1'b1;d=1'b1;
#20;
a=1'b1; b=1'b1; c=1'b0;d=1'b0;
#20;
a=1'b1; b=1'b1; c=1'b0;d=1'b1;
#20;
a=1'b1; b=1'b1; c=1'b1;d=1'b0;
#20;
a=1'b1; b=1'b1; c=1'b1;d=1'b1;
#20;

$display("Test complete");
end
endmodule

dsd_210905324/lab3/2/1/lab2_2.vcd
$date
	Thu Sep  8 10:08:36 2022
$end
$version
	Icarus Verilog
$end
$timescale
	1ns
$end
$scope module lab2_2_tb $end
$var wire 1 ! f $end
$var reg 1 " a $end
$var reg 1 # b $end
$var reg 1 $ c $end
$var reg 1 % d $end
$scope module ex2 $end
$var wire 1 " a $end
$var wire 1 # b $end
$var wire 1 $ c $end
$var wire 1 % d $end
$var wire 1 ! f $end
$var wire 1 & g $end
$upscope $end
$upscope $end
$enddefinitions $end
#0
$dumpvars
0&
0%
0$
0#
0"
1!
$end
#20
1%
#40
0%
1$
#60
0!
1&
1%
#80
0%
0$
1#
#100
1!
0&
1%
#120
0!
1&
0%
1$
#140
1%
#160
1!
0&
0%
0$
0#
1"
#180
1%
#200
0%
1$
#220
0!
1&
1%
#240
0%
0$
1#
#260
1%
#280
0%
1$
#300
1%
