dsd_210905324/lab7/q3/q3.v
module e_to_o_mux(w,s,f);
input [0:7]w;
input [2:0]s;
output reg f;
always @(*)
begin
case(s)
0:f=w[0];
1:f=w[1];
2:f=w[2];
3:f=w[3];
4:f=w[4];
5:f=w[5];
6:f=w[6];
7:f=w[7];
endcase

end
endmodule
module caller(a,b,c,d,f);
input a,b,c,d;
output [3:0]f;
e_to_o_mux e0({1'b0,1'b0,d,1'b1,1'b1,1'b1,1'b1,1'b1},{a,b,c},f[3]);
e_to_o_mux e1({1'b0,1'b1,1'b1,1'b1,1'b1,1'b0,1'b0,1'b0},{b,c,d},f[2]);
e_to_o_mux e2({(~d),d,(~d),d,(~d),d,(~d),d},{a,b,c},f[1]);
e_to_o_mux e3({(~d),(~d),(~d),(~d),(~d),(~d),(~d),(~d)},{a,b,c},f[0]);



endmodule

dsd_210905324/lab7/q3/testbench.v
`timescale 1ns/1ns
`include "q3.v"
module testbench();
reg a,b,c,d;
wire [3:0]f;
integer i;
caller q1(a,b,c,d,f);
initial
begin
    $dumpfile("testbench.vcd");
    $dumpvars(0,testbench);
    for(i=0;i<16;i=i+1)
    begin
    a=i&1;
    b=(i>>1)&1;
    c=(i>>2)&1;
    d=(i>>3)&1;
    #20;
    end

    $display("test complete");
end
endmodule

dsd_210905324/lab7/q3/testbench.vcd
$date
	Thu Oct 20 09:39:33 2022
$end
$version
	Icarus Verilog
$end
$timescale
	1ns
$end
$scope module testbench $end
$var wire 4 ! f [3:0] $end
$var reg 1 " a $end
$var reg 1 # b $end
$var reg 1 $ c $end
$var reg 1 % d $end
$var integer 32 & i [31:0] $end
$scope module q1 $end
$var wire 1 " a $end
$var wire 1 # b $end
$var wire 1 $ c $end
$var wire 1 % d $end
$var wire 4 ' f [3:0] $end
$scope module e0 $end
$var wire 3 ( s [2:0] $end
$var wire 8 ) w [0:7] $end
$var reg 1 * f $end
$upscope $end
$scope module e1 $end
$var wire 3 + s [2:0] $end
$var wire 8 , w [0:7] $end
$var reg 1 - f $end
$upscope $end
$scope module e2 $end
$var wire 3 . s [2:0] $end
$var wire 8 / w [0:7] $end
$var reg 1 0 f $end
$upscope $end
$scope module e3 $end
$var wire 3 1 s [2:0] $end
$var wire 8 2 w [0:7] $end
$var reg 1 3 f $end
$upscope $end
$upscope $end
$upscope $end
$enddefinitions $end
#0
$dumpvars
13
b11111111 2
b0 1
10
b10101010 /
b0 .
0-
b1111000 ,
b0 +
0*
b11111 )
b0 (
b11 '
b0 &
0%
0$
0#
0"
b11 !
$end
#20
00
03
b0 2
b100 !
b100 '
1-
b111111 )
b1 +
b1010101 /
1%
b1 &
#40
b101 !
b101 '
13
b11111111 2
b11111 )
b10101010 /
0%
b1 (
b10 +
b1 .
b1 1
1$
b10 &
#60
03
b0 2
b110 !
b110 '
10
b111111 )
b11 +
b1010101 /
1%
b11 &
#80
13
b11111111 2
b111 !
b111 '
10
b11111 )
b10101010 /
0%
0$
b10 (
b100 +
b10 .
b10 1
1#
b100 &
#100
00
03
b0 2
1*
b1000 !
b1000 '
0-
b111111 )
b101 +
b1010101 /
1%
b101 &
#120
b1001 !
b1001 '
13
b11111111 2
b11111 )
b10101010 /
0%
b11 (
b110 +
b11 .
b11 1
1$
b110 &
#140
03
b0 2
b1010 !
b1010 '
10
b111111 )
b111 +
b1010101 /
1%
b111 &
#160
13
b11111111 2
b1011 !
b1011 '
10
b11111 )
b10101010 /
0%
0$
b0 +
0#
b100 (
b100 .
b100 1
1"
b1000 &
#180
00
03
b0 2
b1100 !
b1100 '
1-
b111111 )
b1 +
b1010101 /
1%
b1001 &
#200
b1101 !
b1101 '
13
b11111111 2
b11111 )
b10101010 /
0%
b101 (
b10 +
b101 .
b101 1
1$
b1010 &
#220
03
b0 2
b1110 !
b1110 '
10
b111111 )
b11 +
b1010101 /
1%
b1011 &
#240
13
b11111111 2
b1111 !
b1111 '
10
b11111 )
b10101010 /
0%
0$
b110 (
b100 +
b110 .
b110 1
1#
b1100 &
#260
00
03
b0 2
b1000 !
b1000 '
0-
b111111 )
b101 +
b1010101 /
1%
b1101 &
#280
b1001 !
b1001 '
13
b11111111 2
b11111 )
b10101010 /
0%
b111 (
b110 +
b111 .
b111 1
1$
b1110 &
#300
03
b0 2
b1010 !
b1010 '
10
b111111 )
b111 +
b1010101 /
1%
b1111 &
#320
b10000 &
