dsd_210905324/lab2/1/1/lab2_1.v
module lab2_1(a, b, c,d, m);
input a, b,c,d;
output m;

assign m =(c&d) | (b&(~c)&(~d)) | ((~a)&b) | (c&(~b));

endmodule

dsd_210905324/lab2/1/2/lab2_1_tb.v
`timescale 1ns/1ns
`include "lab2_1.v"
//Name of the Verilog file
module lab2_1_tb();
reg a,b,c,d;
//Input
wire m;
//Output
lab2_1 ex2(a,b,c,d,m); //Instantiation of the module
initial
begin
$dumpfile("lab2_1.vcd");
$dumpvars(0, lab2_1_tb);
a=1'b0; b=1'b0; c=1'b0;d=1'b0;
#20;

a=1'b0; b=1'b0; c=1'b0;d=1'b1;
#20;
a=1'b0; b=1'b0; c=1'b1;d=1'b0;
#20;
a=1'b0; b=1'b0; c=1'b1;d=1'b1;
#20;
a=1'b0; b=1'b1; c=1'b0;d=1'b0;
#20;
a=1'b0; b=1'b1; c=1'b0;d=1'b1;
#20;
a=1'b0; b=1'b1; c=1'b1;d=1'b0;
#20;
a=1'b0; b=1'b1; c=1'b1;d=1'b1;
#20;
a=1'b1; b=1'b0; c=1'b0;d=1'b0;
#20;
a=1'b1; b=1'b0; c=1'b0;d=1'b1;
#20;
a=1'b1; b=1'b0; c=1'b1;d=1'b0;
#20;
a=1'b1; b=1'b0; c=1'b1;d=1'b1;
#20;
a=1'b1; b=1'b1; c=1'b0;d=1'b0;
#20;
a=1'b1; b=1'b1; c=1'b0;d=1'b1;
#20;
a=1'b1; b=1'b1; c=1'b1;d=1'b0;
#20;
a=1'b1; b=1'b1; c=1'b1;d=1'b1;
#20;

$display("Test complete");
end
endmodule

dsd_210905324/lab2/1/1/lab2_1.vcd
$date
	Thu Sep  1 09:25:25 2022
$end
$version
	Icarus Verilog
$end
$timescale
	1ns
$end
$scope module lab2_1_tb $end
$var wire 1 ! m $end
$var reg 1 " a $end
$var reg 1 # b $end
$var reg 1 $ c $end
$var reg 1 % d $end
$scope module ex2 $end
$var wire 1 " a $end
$var wire 1 # b $end
$var wire 1 $ c $end
$var wire 1 % d $end
$var wire 1 ! m $end
$upscope $end
$upscope $end
$enddefinitions $end
#0
$dumpvars
0%
0$
0#
0"
0!
$end
#20
1%
#40
1!
0%
1$
#60
1%
#80
0%
0$
1#
#100
1%
#120
0%
1$
#140
1%
#160
0!
0%
0$
0#
1"
#180
1%
#200
1!
0%
1$
#220
1%
#240
1!
0%
0$
1#
#260
0!
1%
#280
0%
1$
#300
1!
1%
